f1_replay/__init__.py
f1_replay/config.py
f1_replay/api/__init__.py
f1_replay/api/app.py
f1_replay/api/cli.py
f1_replay/api/serializers.py
f1_replay/loaders/__init__.py
f1_replay/loaders/core/__init__.py
f1_replay/loaders/core/client.py
f1_replay/loaders/core/mapping.py
f1_replay/loaders/seasons/__init__.py
f1_replay/loaders/seasons/processor.py
f1_replay/loaders/session/__init__.py
f1_replay/loaders/session/order.py
f1_replay/loaders/session/processor.py
f1_replay/loaders/session/telemetry.py
f1_replay/loaders/session/weather.py
f1_replay/loaders/weekend/__init__.py
f1_replay/loaders/weekend/light_telemetry.py
f1_replay/loaders/weekend/processor.py
f1_replay/managers/__init__.py
f1_replay/managers/dataloader.py
f1_replay/managers/race_manager.py
f1_replay/models/__init__.py
f1_replay/models/base.py
f1_replay/models/event.py
f1_replay/models/results.py
f1_replay/models/session.py
f1_replay/models/weekend.py
f1_replay/services/__init__.py
f1_replay/services/track_finder.py
f1_replay/services/track_transformer.py
f1_replay/tools/__init__.py
f1_replay/tools/weekend_plot.py
f1_replay/wrappers/__init__.py
f1_replay/wrappers/race_weekend.py
f1_replay/wrappers/session.py
f1_replay-0.1.10.dist-info/METADATA
f1_replay-0.1.10.dist-info/WHEEL
f1_replay-0.1.10.dist-info/entry_points.txt
f1_replay-0.1.10.dist-info/top_level.txt
f1_replay-0.1.10.dist-info/RECORD
